anadb_tools/__init__.py
anadb_tools/anabroker.py
anadb_tools/anadb.py
anadb_tools/appdb.py
anadb_tools/common.py
anadb_tools/data.py
anadb_tools/database.py
anadb_tools/exceptions.py
anadb_tools/patterns.py
anadb_tools/redcache.py
anadb_tools/cli/__init__.py
anadb_tools/cli/activate.py
anadb_tools/cli/assign.py
anadb_tools/cli/cleanup.py
anadb_tools/cli/deactivate.py
anadb_tools/cli/deploy.py
anadb_tools/cli/gather_utilization.py
anadb_tools/cli/migrate.py
anadb_tools/cli/move.py
anadb_tools/cli/orphans.py
anadb_tools/cli/recency.py
anadb_tools/cli/s3backup.py
anadb_tools/cli/skeleton.py
anadb_tools-0.12.2.dist-info/DESCRIPTION.rst
anadb_tools-0.12.2.dist-info/METADATA
anadb_tools-0.12.2.dist-info/RECORD
anadb_tools-0.12.2.dist-info/WHEEL
anadb_tools-0.12.2.dist-info/entry_points.txt
anadb_tools-0.12.2.dist-info/metadata.json
anadb_tools-0.12.2.dist-info/top_level.txt
anadb_tools-0.12.2.dist-info/zip-safe
