Metadata-Version: 2.0
Name: anadb-tools
Version: 0.12.2
Summary: A collection tools for managing the analytics databases
Home-page: https://github.aweber.com/dba/anadb-tools/
Author: Gavin M. Roy
Author-email: gavinr@aweber.com
License: UNKNOWN
Platform: UNKNOWN
Classifier: Development Status :: 4 - Beta
Classifier: Programming Language :: Python :: 3
Classifier: Programming Language :: Python :: 3.5
Classifier: Programming Language :: Python :: 3.6
Classifier: Programming Language :: Python :: Implementation :: CPython
Requires-Dist: arrow
Requires-Dist: boto3
Requires-Dist: consulate
Requires-Dist: pgpasslib
Requires-Dist: psycopg2
Requires-Dist: redis
Requires-Dist: requests
